flask_hype
