Metadata-Version: 1.1
Name: flask-hype
Version: 0.1.2
Summary: Flask extension for hype
Home-page: https://github.com/bninja/flask-hype
Author: egon
Author-email: egon@gb.com
License: BSD
Platform: any
Classifier: Environment :: Web Environment
Classifier: Intended Audience :: Developers
Classifier: License :: OSI Approved :: BSD License
Classifier: Operating System :: OS Independent
Classifier: Programming Language :: Python
Classifier: Topic :: Internet :: WWW/HTTP :: Dynamic Content
Classifier: Topic :: Software Development :: Libraries :: Python Modules
